snipster/__init__.py
snipster/__main__.py
snipster/cli.py
snipster/cli_snippet_service.py
snipster/db.py
snipster/exceptions.py
snipster/models.py
snipster/repo.py
pdc_snipster_cli-0.1.0.dist-info/METADATA
pdc_snipster_cli-0.1.0.dist-info/WHEEL
pdc_snipster_cli-0.1.0.dist-info/entry_points.txt
pdc_snipster_cli-0.1.0.dist-info/RECORD
