Metadata-Version: 2.4
Name: pdc-snipster-cli
Version: 0.1.0
Summary: Code snippet repository
Author-email: Brandon Brown <afrobot@gmail.com>
Requires-Python: >=3.13
Requires-Dist: alembic>=1.16.4
Requires-Dist: fastapi[all]>=0.116.1
Requires-Dist: httpx>=0.28.1
Requires-Dist: psycopg[binary]>=3.2.9
Requires-Dist: python-dotenv>=1.1.1
Requires-Dist: rapidfuzz>=3.13.0
Requires-Dist: reflex-hosting-cli>=0.1.55
Requires-Dist: reflex>=0.8.6
Requires-Dist: rich>=14.0.0
Requires-Dist: sqlmodel>=0.0.24
Requires-Dist: typer>=0.16.0
